yap_torrent/__init__.py
yap_torrent/application.py
yap_torrent/config.py
yap_torrent/env.py
yap_torrent/logs.py
yap_torrent/system.py
yap_torrent/upnp.py
yap_torrent/utils.py
yap_torrent/components/extensions.py
yap_torrent/components/peer_ec.py
yap_torrent/components/piece_ec.py
yap_torrent/components/torrent_ec.py
yap_torrent/components/tracker_ec.py
yap_torrent/dht/bt_dht_messages.py
yap_torrent/dht/connection.py
yap_torrent/dht/tokens.py
yap_torrent/dht/utils.py
yap_torrent/dht/routing/bucket.py
yap_torrent/dht/routing/nodes.py
yap_torrent/dht/routing/table.py
yap_torrent/plugins/__init__.py
yap_torrent/plugins/torrent_plugin.py
yap_torrent/protocol/__init__.py
yap_torrent/protocol/bt_ext_messages.py
yap_torrent/protocol/bt_main_messages.py
yap_torrent/protocol/connection.py
yap_torrent/protocol/extensions.py
yap_torrent/protocol/magnet.py
yap_torrent/protocol/message.py
yap_torrent/protocol/parser.py
yap_torrent/protocol/structures.py
yap_torrent/protocol/tracker.py
yap_torrent/systems/__init__.py
yap_torrent/systems/announce_system.py
yap_torrent/systems/bt_choke_system.py
yap_torrent/systems/bt_dht_system.py
yap_torrent/systems/bt_download_system.py
yap_torrent/systems/bt_ext_metadata_system.py
yap_torrent/systems/bt_extension_system.py
yap_torrent/systems/bt_intrest_system.py
yap_torrent/systems/bt_local_data_system.py
yap_torrent/systems/bt_magnet_system.py
yap_torrent/systems/bt_upload_system.py
yap_torrent/systems/bt_validation_system.py
yap_torrent/systems/peer_system.py
yap_torrent/systems/piece_system.py
yap_torrent/systems/torrents_system.py
yap_torrent/systems/watch_system.py
yap_torrent-0.1.2.dist-info/METADATA
yap_torrent-0.1.2.dist-info/WHEEL
yap_torrent-0.1.2.dist-info/entry_points.txt
yap_torrent-0.1.2.dist-info/licenses/LICENSE
yap_torrent-0.1.2.dist-info/RECORD
