Metadata-Version: 2.4
Name: yap_torrent
Version: 0.1.2
Summary: BitTorrent client implemented in python
Project-URL: Homepage, https://github.com/Angel777d/yap_torrent
Project-URL: Issues, https://github.com/Angel777d/yap_torrent/issues
Author-email: Angelovich <angel777da@gmail.com>
License-Expression: MIT
License-File: LICENSE
Keywords: BitTorrent,DHT,Torrent
Classifier: Development Status :: 3 - Alpha
Classifier: Intended Audience :: Developers
Classifier: Intended Audience :: Education
Classifier: Operating System :: OS Independent
Classifier: Programming Language :: Python :: 3
Classifier: Programming Language :: Python :: 3.13
Classifier: Programming Language :: Python :: 3.14
Requires-Python: >=3.13
Requires-Dist: angelovich-core
Requires-Dist: requests
